CHANGES.txt
README.rst
development.ini
setup.cfg
setup.py
docs/LICENSE.txt
kotti_theme_readable/__init__.py
kotti_theme_readable.egg-info/PKG-INFO
kotti_theme_readable.egg-info/SOURCES.txt
kotti_theme_readable.egg-info/dependency_links.txt
kotti_theme_readable.egg-info/entry_points.txt
kotti_theme_readable.egg-info/not-zip-safe
kotti_theme_readable.egg-info/requires.txt
kotti_theme_readable.egg-info/top_level.txt
kotti_theme_readable/static/bootstrap.css
kotti_theme_readable/static/bootstrap.min.css