Metadata-Version: 1.0
Name: kotti-theme-readable
Version: 0.2
Summary: Readable theme from http://bootswatch.com/readable/ for Kotti
Home-page: https://github.com/geojeff/kotti_theme_readable
Author: Jeff Pittman
Author-email: geojeff@me.com
License: BSD-derived (http://www.repoze.org/LICENSE.txt)
Keywords: kotti theme
Platform: UNKNOWN
Classifier: Programming Language :: Python
Classifier: Framework :: Pyramid
Classifier: License :: Repoze Public License
